examples/__init__.py
llmservice/ prompts.py
llmservice/__init__.py
llmservice/base_agent.py
llmservice/base_service.py
llmservice/debug_tools.py
llmservice/example_agent_usage.py
llmservice/gates.py
llmservice/generation_engine.py
llmservice/generation_engine_with_pipelines.py
llmservice/live_metrics.py
llmservice/llm_handler copy.py
llmservice/llm_handler.py
llmservice/myllmservice.py
llmservice/schemas.py
llmservice/simple_agent_example.py
llmservice/telemetry.py
llmservice/utils.py
llmservice/providers/__init__.py
llmservice/providers/base.py
llmservice/providers/claude_provider.py
llmservice/providers/new_openai_provider.py
llmservice/providers/ollama_provider.py
llmservice/providers/openai_provider.py
llmservice/structured_schemas/__init__.py
llmservice/structured_schemas/structured_outputs.py
llmservice-0.3.0.dist-info/METADATA
llmservice-0.3.0.dist-info/WHEEL
llmservice-0.3.0.dist-info/top_level.txt
llmservice-0.3.0.dist-info/RECORD
