Metadata-Version: 2.4
Name: llmservice
Version: 0.3.0
Summary: A lightweight, production-ready service layer for modular, rate-aware LLM integrations
Author: Enes Kuzucu
Classifier: Development Status :: 3 - Alpha
Classifier: Intended Audience :: Developers
Classifier: License :: OSI Approved :: MIT License
Classifier: Programming Language :: Python :: 3
Classifier: Programming Language :: Python :: 3.7
Classifier: Programming Language :: Python :: 3.8
Classifier: Programming Language :: Python :: 3.9
Classifier: Programming Language :: Python :: 3.10
Classifier: Operating System :: OS Independent
Requires-Python: >=3.8
Requires-Dist: langchain
Requires-Dist: langchain-community
Requires-Dist: langchain-openai
Requires-Dist: langchain-ollama
Requires-Dist: string2dict
Requires-Dist: indented_logger
Requires-Dist: pyyaml
Requires-Dist: tqdm
Requires-Dist: python-dotenv
Requires-Dist: pytest
Dynamic: author
Dynamic: classifier
Dynamic: description
Dynamic: description-content-type
Dynamic: requires-dist
Dynamic: requires-python
Dynamic: summary
